{
  "request_id": "220724160021_48b166cf-b50a-566b-a769-ea30add88796",
  "status": "invalid",
  "request": {
    "target_credentials": "d1c0c221-4a2f-4c3d-8a2d-ff57308ce5fe",
    "source_settings": {
      "$schema": "https://s.dev.y42.dev/integrations/sql_model/0.0.0/source.json",
      "tablesOrder": [
        "table_1"
      ]
    },
    "table_settings": {
      "$schema": "https://s.dev.y42.dev/integrations/sql_model/0.0.0/table.json"
    },
    "created_at": "2022-07-24T16:00:21.555981+00:00",
    "target": {
      "storage": {
        "type": "githubapp",
        "path": "/src/Models/SQL/My_SQL_Model/table_1",
        "id": "6:909f4b48-879e-4a1e-acca-6c1a4fcfa2ff",
        "branch": "main"
      },
      "info": {
        "app_id": "24758422",
        "owner": "goes-funky",
        "repo": "git-data-mock-dev-cluster-v2",
        "commit_sha": "51dab281ba4823155a6685791c85da4faf7c93af"
      }
    },
    "context": {
      "company_id": 6,
      "company_slug": "y42-demo",
      "triggered_by_type": "orchestration",
      "triggered_by_id": "/src/Orchestrations/first/.y42/run_760e6ce1-e043-46e2-af8b-bc921660aec4.json",
      "trial": true
    },
    "previous_import_id": "223e23d3-0eef-560c-9b1f-a743e947e58c",
    "previous_table_id": "220720152511_223e23d3-0eef-560c-9b1f-a743e947e58c"
  },
  "created_at": "2022-07-24T16:00:21.555981+00:00",
  "failed_at": "2022-07-24T16:03:21.744919+00:00",
  "error_code": 422,
  "error_message": "",
  "_signature": "RndsZoykrXOjr+07DMa44fa39jH9t0ZrP2DFgzkcNGp7fPxpgPBB3WfZHBfeFSb9JhC3KRQwf0J6gUhdlOJACQ=="
}
