{
  "request_id": "220714110015_6a4f661a-5ce8-5414-909c-128b16452161",
  "status": "pending",
  "request": {
    "source_credentials": "616d1d39-3cac-493f-be89-d52df43ab563",
    "target_credentials": "d1c0c221-4a2f-4c3d-8a2d-ff57308ce5fe",
    "source_settings": {
      "$schema": "https://s.dev.y42.dev/integrations/facebook-pages/0.0.0/source.json",
      "parent_id": "102004408442825,105306121815794,110203024472908",
      "start_date": "2021-06-15T15:40:24Z"
    },
    "table_settings": {
      "$schema": "https://s.dev.y42.dev/integrations/facebook-pages/0.0.0/table",
      "columns": [
        "name",
        "period",
        "value",
        "context",
        "end_time",
        "title",
        "description",
        "id",
        "page_id"
      ],
      "import": "page_insight_website_clicks"
    },
    "created_at": "2022-07-14T11:00:15.572141+00:00",
    "target": {
      "storage": {
        "type": "githubapp",
        "path": "/src/Integrations/facebook_pages/page_insight_website_clicks",
        "id": "6:909f4b48-879e-4a1e-acca-6c1a4fcfa2ff",
        "branch": "main"
      },
      "info": {
        "app_id": "24758422",
        "owner": "goes-funky",
        "repo": "git-data-mock-dev-cluster-v2",
        "commit_sha": "104fc25f818e30261885a02c328a10e7a6ca36b9"
      }
    },
    "context": {
      "company_id": 6,
      "company_slug": "y42-demo",
      "triggered_by_type": "orchestration",
      "triggered_by_id": "/src/Orchestrations/second/.y42/run_54bd45e7-fd68-4e9a-b35b-6440815b4de2.json",
      "trial": true
    },
    "state": {
      "bookmarks": {
        "page_insight_website_clicks": {
          "partitions": [
            {
              "context": {
                "page_id": "102004408442825"
              }
            },
            {
              "context": {
                "page_id": "105306121815794"
              }
            },
            {
              "context": {
                "page_id": "110203024472908"
              }
            }
          ]
        }
      },
      "schema_hash": "9ae04295eb7ef2f09742bff479d3c672"
    },
    "previous_import_id": "b48af221-c2a3-5e82-a7a7-22f102f71eeb",
    "previous_table_id": "220714104507_b48af221-c2a3-5e82-a7a7-22f102f71eeb"
  },
  "created_at": "2022-07-14T11:00:15.572141+00:00",
  "details": {
    "invalid_rows": 0,
    "export_finished_at": "2022-07-14T11:00:50.590815+00:00",
    "external_state": {
      "bookmarks": {
        "page_insight_website_clicks": {
          "partitions": [
            {
              "context": {
                "page_id": "102004408442825"
              }
            },
            {
              "context": {
                "page_id": "105306121815794"
              }
            },
            {
              "context": {
                "page_id": "110203024472908"
              }
            }
          ]
        }
      },
      "schema_hash": "9ae04295eb7ef2f09742bff479d3c672"
    },
    "write_disposition": "TRUNCATE",
    "external_id": "d176421b-02d8-4b3a-8c47-dda3c62a945f",
    "storage_file": "gs://y42_newdevspace_ee3d738c7fe64ddfa1063f679c5b1048/userUploads/v2/tap-facebook-pages/72b5e4cc-3f07-459f-bfab-23288e3dd5c2",
    "partial": false
  },
  "_signature": "uKvMbeeqhywJwlB1wRWMtwCsvcP65El0Pvo2VExOTKqnizv9zMFiM56ELQvrTiA+bNywyiaMi8T+16zP++NsAw=="
}
