{
  "request_id": "220723074009_1e72bd4d-17db-5b8c-bbda-a77e6d416d93",
  "status": "ready",
  "request": {
    "source_credentials": "616d1d39-3cac-493f-be89-d52df43ab563",
    "target_credentials": "d1c0c221-4a2f-4c3d-8a2d-ff57308ce5fe",
    "source_settings": {
      "$schema": "https://s.dev.y42.dev/integrations/facebook-pages/0.0.0/source.json",
      "parent_id": "102004408442825,105306121815794,110203024472908",
      "start_date": "2021-06-15T15:40:24Z"
    },
    "table_settings": {
      "$schema": "https://s.dev.y42.dev/integrations/facebook-pages/0.0.0/table",
      "columns": [
        "name",
        "period",
        "value",
        "context",
        "end_time",
        "title",
        "description",
        "id",
        "page_id"
      ],
      "import": "page_insight_website_clicks"
    },
    "created_at": "2022-07-23T07:40:09.089721+00:00",
    "target": {
      "storage": {
        "type": "githubapp",
        "path": "/src/Integrations/facebook_pages/page_insight_website_clicks",
        "id": "6:909f4b48-879e-4a1e-acca-6c1a4fcfa2ff",
        "branch": "main"
      },
      "info": {
        "app_id": "24758422",
        "owner": "goes-funky",
        "repo": "git-data-mock-dev-cluster-v2",
        "commit_sha": "398db21106359e3f686d5f1eadb67f18bd50a488"
      }
    },
    "context": {
      "company_id": 6,
      "company_slug": "y42-demo",
      "triggered_by_type": "orchestration",
      "triggered_by_id": "/src/Orchestrations/first/.y42/run_aac6a2b7-75d8-46df-bc09-6782c3538600.json",
      "trial": true
    },
    "state": {
      "bookmarks": {
        "page_insight_website_clicks": {
          "partitions": [
            {
              "context": {
                "page_id": "102004408442825"
              }
            },
            {
              "context": {
                "page_id": "105306121815794"
              }
            },
            {
              "context": {
                "page_id": "110203024472908"
              }
            }
          ]
        }
      },
      "schema_hash": "9ae04295eb7ef2f09742bff479d3c672"
    },
    "previous_import_id": "e3cbd215-c61d-5bdc-9d03-d8ebc14d44d8",
    "previous_table_id": "220723072009_e3cbd215-c61d-5bdc-9d03-d8ebc14d44d8"
  },
  "created_at": "2022-07-23T07:40:09.089721+00:00",
  "details": {
    "invalid_rows": 0,
    "export_finished_at": "2022-07-23T07:40:56.171229+00:00",
    "external_state": {
      "bookmarks": {
        "page_insight_website_clicks": {
          "partitions": [
            {
              "context": {
                "page_id": "102004408442825"
              }
            },
            {
              "context": {
                "page_id": "105306121815794"
              }
            },
            {
              "context": {
                "page_id": "110203024472908"
              }
            }
          ]
        }
      },
      "schema_hash": "9ae04295eb7ef2f09742bff479d3c672"
    },
    "write_disposition": "TRUNCATE",
    "external_id": "368399b0-b7fb-4193-97da-933a2ccf0401",
    "storage_file": "gs://y42_newdevspace_ee3d738c7fe64ddfa1063f679c5b1048/userUploads/v2/tap-facebook-pages/b9ffd6ce-4293-458f-8eb0-4dd76d4b3757",
    "partial": false,
    "import_finished_at": "2022-07-23T07:41:32.459656+00:00",
    "row_count": 4341,
    "current_import_row_count": 4341,
    "size_in_bytes": 923002,
    "previous_id": "e3cbd215-c61d-5bdc-9d03-d8ebc14d44d8",
    "columns": [
      {
        "field_name": "name",
        "data_type": "STRING",
        "external_data_type": "STRING"
      },
      {
        "field_name": "period",
        "data_type": "STRING",
        "external_data_type": "STRING"
      },
      {
        "field_name": "value",
        "data_type": "INTEGER",
        "external_data_type": "INTEGER"
      },
      {
        "field_name": "context",
        "data_type": "STRING",
        "external_data_type": "STRING"
      },
      {
        "field_name": "end_time",
        "data_type": "STRING",
        "external_data_type": "STRING"
      },
      {
        "field_name": "title",
        "data_type": "STRING",
        "external_data_type": "STRING"
      },
      {
        "field_name": "description",
        "data_type": "STRING",
        "external_data_type": "STRING"
      },
      {
        "field_name": "id",
        "data_type": "STRING",
        "external_data_type": "STRING"
      },
      {
        "field_name": "page_id",
        "data_type": "STRING",
        "external_data_type": "STRING"
      }
    ],
    "table_name": "220723074009_1e72bd4d-17db-5b8c-bbda-a77e6d416d93",
    "external_url": "https://console.cloud.google.com/bigquery?p=datos-tech&d=y42_newdevspace_ee3d738c7fe64ddfa1063f679c5b1048&t=220723074009_1e72bd4d-17db-5b8c-bbda-a77e6d416d93&page=table"
  },
  "finished_at": "2022-07-23T07:41:32.459793+00:00",
  "_signature": "jIhFY78x8ToDVwD7miDg1BDfLT2VG3o48MAzY3FGCxk2WtxAqputmjIadZB19TuZdYS1pN0VLVG+f6K3vKxhDQ=="
}
