{
  "request_id": "220715040015_90502f08-c3e4-54c1-8346-4d6cb433836b",
  "status": "pending",
  "request": {
    "source_credentials": "616d1d39-3cac-493f-be89-d52df43ab563",
    "target_credentials": "d1c0c221-4a2f-4c3d-8a2d-ff57308ce5fe",
    "source_settings": {
      "$schema": "https://s.dev.y42.dev/integrations/facebook-pages/0.0.0/source.json",
      "parent_id": "102004408442825,105306121815794,110203024472908",
      "start_date": "2021-06-15T15:40:24Z"
    },
    "table_settings": {
      "$schema": "https://s.dev.y42.dev/integrations/facebook-pages/0.0.0/table",
      "columns": [
        "name",
        "period",
        "value",
        "context",
        "end_time",
        "title",
        "description",
        "id",
        "page_id"
      ],
      "import": "page_insight_website_clicks"
    },
    "created_at": "2022-07-15T04:00:15.047074+00:00",
    "target": {
      "storage": {
        "type": "githubapp",
        "path": "/src/Integrations/facebook_pages/page_insight_website_clicks",
        "id": "6:909f4b48-879e-4a1e-acca-6c1a4fcfa2ff",
        "branch": "main"
      },
      "info": {
        "app_id": "24758422",
        "owner": "goes-funky",
        "repo": "git-data-mock-dev-cluster-v2",
        "commit_sha": "bf9f3c3aa2548b3a4af6c0f511db2b1d416d8eb4"
      }
    },
    "context": {
      "company_id": 6,
      "company_slug": "y42-demo",
      "triggered_by_type": "orchestration",
      "triggered_by_id": "/src/Orchestrations/second/.y42/run_2a302d04-666b-48bb-b39e-0f689407e832.json",
      "trial": true
    },
    "state": {
      "bookmarks": {
        "page_insight_website_clicks": {
          "partitions": [
            {
              "context": {
                "page_id": "102004408442825"
              }
            },
            {
              "context": {
                "page_id": "105306121815794"
              }
            },
            {
              "context": {
                "page_id": "110203024472908"
              }
            }
          ]
        }
      },
      "schema_hash": "9ae04295eb7ef2f09742bff479d3c672"
    },
    "previous_import_id": "67651e65-eea8-5c1f-a99c-55fed34fbe81",
    "previous_table_id": "220715034507_67651e65-eea8-5c1f-a99c-55fed34fbe81"
  },
  "created_at": "2022-07-15T04:00:15.047074+00:00",
  "details": {
    "invalid_rows": 0,
    "export_finished_at": "2022-07-15T04:01:08.051208+00:00",
    "external_state": {
      "bookmarks": {
        "page_insight_website_clicks": {
          "partitions": [
            {
              "context": {
                "page_id": "102004408442825"
              }
            },
            {
              "context": {
                "page_id": "105306121815794"
              }
            },
            {
              "context": {
                "page_id": "110203024472908"
              }
            }
          ]
        }
      },
      "schema_hash": "9ae04295eb7ef2f09742bff479d3c672"
    },
    "write_disposition": "TRUNCATE",
    "external_id": "6ba6cecd-85aa-47c1-ab19-4be8a647f2bd",
    "storage_file": "gs://y42_newdevspace_ee3d738c7fe64ddfa1063f679c5b1048/userUploads/v2/tap-facebook-pages/8bb167ee-4668-4690-b499-a369efbe7bad",
    "partial": false
  },
  "_signature": "Td+4OaTQ3Zo1iA91nXOqpL4ciR5oxOEjYh5pXg88ite8u1iIk7YvzGUzk6GMqVVQExp/v9ymRJPlMYEOlLrZDA=="
}
