{
  "request_id": "220715194507_3a904b3b-570a-50c7-aec1-cdc135edca98",
  "status": "pending",
  "details": {
    "invalid_rows": 0,
    "export_finished_at": "2022-07-15T19:46:06.087185+00:00",
    "external_state": {
      "bookmarks": {
        "page_insight_website_clicks": {
          "partitions": [
            {
              "context": {
                "page_id": "102004408442825"
              }
            },
            {
              "context": {
                "page_id": "105306121815794"
              }
            },
            {
              "context": {
                "page_id": "110203024472908"
              }
            }
          ]
        }
      },
      "schema_hash": "9ae04295eb7ef2f09742bff479d3c672"
    },
    "write_disposition": "TRUNCATE",
    "external_id": "9906b96a-3fb1-48e5-aaf6-0ed9ea43309c",
    "storage_file": "gs://y42_newdevspace_ee3d738c7fe64ddfa1063f679c5b1048/userUploads/v2/tap-facebook-pages/1e720487-c06e-485b-bc0e-74e27d0c1cf6",
    "partial": false
  },
  "_signature": "XWf8JJlKjGPPCIp/Mg11fee5dbdfW7Ft754yZlhcmK3ZzyusNMM8A/5ge9nJq16nHhQZQu44+IGhFbtqvwjyBA=="
}
