{
  "request_id": "220706083310_e82af1fa-2a3e-57d5-99c1-6dd6225c58fc",
  "status": "pending",
  "request": {
    "source_credentials": "7b8d4f61-03bd-42e9-b1ff-0d8c72af7f4c",
    "target_credentials": "d1c0c221-4a2f-4c3d-8a2d-ff57308ce5fe",
    "source_settings": {
      "$schema": "https://s.dev.y42.dev/integrations/instagram/0.0.0/source.json",
      "parent_id": "102004408442825",
      "start_date": "2021-06-15T17:03:18Z"
    },
    "table_settings": {
      "$schema": "https://s.dev.y42.dev/integrations/instagram/0.0.0/table",
      "columns": [
        "page_id",
        "business_account_id",
        "date",
        "follower_count",
        "get_directions_clicks",
        "impressions",
        "phone_call_clicks",
        "profile_views",
        "reach",
        "text_message_clicks",
        "website_clicks",
        "impressions_week",
        "reach_week",
        "impressions_days_28",
        "reach_days_28",
        "online_followers"
      ],
      "import": "user_insights",
      "_datos_write_settings": {
        "max_flatten_depth": 0,
        "decimals": false
      }
    },
    "created_at": "2022-07-06T08:33:10.307475+00:00",
    "target": {
      "storage": {
        "type": "githubapp",
        "path": "/src/Integrations/instagram/user_insights",
        "id": "6:909f4b48-879e-4a1e-acca-6c1a4fcfa2ff",
        "branch": "main"
      },
      "info": {
        "app_id": "24758422",
        "owner": "goes-funky",
        "repo": "git-data-mock-dev-cluster-v2",
        "commit_sha": "d82b34ed4764b39bb93f5e9ab0f00ef62334ec1e"
      }
    },
    "context": {
      "company_id": 6,
      "company_slug": "y42-demo",
      "triggered_by_type": "user",
      "triggered_by_id": "85",
      "trial": true
    }
  },
  "created_at": "2022-07-06T08:33:10.307475+00:00",
  "details": {
    "invalid_rows": 0,
    "export_finished_at": "2022-07-06T08:34:07.342502+00:00",
    "external_state": {
      "schema_hash": "1d2c53aec4369441c196d1da5ef49ed2"
    },
    "write_disposition": "TRUNCATE",
    "external_id": "89044c64-4a2f-4114-8f41-5e131f417c08",
    "storage_file": "gs://y42_newdevspace_ee3d738c7fe64ddfa1063f679c5b1048/userUploads/v2/tap-instagram/5888048e-deb0-48dd-a9f9-74980b3ff1cc",
    "partial": false
  },
  "_signature": "8ho8pqiUSJXKN4RAWF0xWd5XaatsdzSOLTIWNC7Ju99IATuN5dhF5wzVM/2PdA71460wJYcVZLPDd+4hyjsDAw=="
}
