{
  "request_id": "220615131332_fc4ed166-f14b-52f3-9c95-88de3f7e5664",
  "status": "pending",
  "request": {
    "source_credentials": "d01d3522-28b4-41f2-8458-693d311d900e",
    "target_credentials": "d1c0c221-4a2f-4c3d-8a2d-ff57308ce5fe",
    "source_settings": {
      "$schema": "https://s.dev.y42.dev/integrations/mysql/0.0.0/source.json"
    },
    "table_settings": {
      "$schema": "https://s.dev.y42.dev/integrations/mysql/0.0.0/table",
      "columns": [
        "object_schema",
        "object_name",
        "allocated",
        "data",
        "pages",
        "pages_hashed",
        "pages_old",
        "rows_cached"
      ],
      "import": "sys-x$innodb_buffer_stats_by_table"
    },
    "created_at": "2022-06-15T13:13:32.155470+00:00",
    "target": {
      "storage": {
        "type": "githubapp",
        "path": "/src/Integrations/My_SQL_integration/x$innodb_buffer_stats_by_table",
        "id": "6:909f4b48-879e-4a1e-acca-6c1a4fcfa2ff",
        "branch": "main"
      },
      "info": {
        "app_id": "24758422",
        "owner": "goes-funky",
        "repo": "git-data-mock-dev-cluster-v2",
        "commit_sha": "ab42e670adcc2f70b7b3d6d96ed2d767e15562c0"
      }
    },
    "context": {
      "company_id": 6,
      "company_slug": "y42-demo",
      "triggered_by_type": "user",
      "triggered_by_id": "95",
      "trial": true
    }
  },
  "created_at": "2022-06-15T13:13:32.155470+00:00",
  "details": {
    "invalid_rows": 0,
    "export_finished_at": "2022-06-15T13:14:48.270581+00:00",
    "external_state": {
      "bookmarks": {
        "sys-x$innodb_buffer_stats_by_table": {
          "initial_full_table_complete": true
        }
      },
      "currently_syncing": null,
      "schema_hash": "c88d34b9213cdd2160077becdff3892c"
    },
    "write_disposition": "TRUNCATE",
    "external_id": "9492463d-c5b6-4ac4-8822-ebf31ff73695",
    "storage_file": "gs://y42_newdevspace_ee3d738c7fe64ddfa1063f679c5b1048/userUploads/v2/tap-mysql/e9fc134e-7581-46af-905b-26edb7e67dbe",
    "partial": false
  },
  "_signature": "n6Ns1dYO7an17JHODKJ0MbboKtmtNWYTJqSp5tFoGjsCKT+L5WTMV8pX6UiaOCWt+EUHb3gSxPgrxDA+SeYnDw=="
}
